cmus_notify/__init__.py
cmus_notify/cmus_notify.py
cmus_notify/configurations.py
cmus_notify/constants.py
cmus_notify/formatters.py
cmus_notify/notifications.py
cmus_notify/options.py
cmus_notify/parsers.py
cmus_notify/types.py
cmus_notify-1.4.2.dist-info/licenses/LICENSE
cmus_notify-1.4.2.dist-info/METADATA
cmus_notify-1.4.2.dist-info/WHEEL
cmus_notify-1.4.2.dist-info/entry_points.txt
cmus_notify-1.4.2.dist-info/top_level.txt
cmus_notify-1.4.2.dist-info/RECORD
