Metadata-Version: 2.4
Name: cmus-notify
Version: 1.4.2
Summary: A package for displaying Cmus current status in notifications
Author-email: Antoine Gagné <AntoineGagne@users.noreply.github.com>
Maintainer-email: Antoine Gagné <AntoineGagne@users.noreply.github.com>
License-Expression: MIT
Project-URL: Homepage, https://github.com/AntoineGagne/cmus-notify
Project-URL: Repository, https://github.com/AntoineGagne/cmus-notify
Project-URL: Bug Tracker, https://github.com/AntoineGagne/cmus-notify/issues
Classifier: Development Status :: 5 - Production/Stable
Classifier: Operating System :: POSIX :: Linux
Classifier: Programming Language :: Python :: 3.9
Classifier: Programming Language :: Python :: 3.10
Classifier: Programming Language :: Python :: 3.11
Classifier: Programming Language :: Python :: 3.12
Classifier: Programming Language :: Python :: 3.13
Classifier: Programming Language :: Python :: 3.14
Classifier: Topic :: Multimedia :: Sound/Audio
Requires-Python: >=3.9
License-File: LICENSE
Requires-Dist: desktop-notify~=1.3; platform_system == "Linux"
Dynamic: license-file
